<?xml version="1.0" encoding="UTF-8"?>
<element class="edu.cmu.cs.stage3.alice.core.response.PropertyAnimation" version="2.001">
    <property
        criterionClass="edu.cmu.cs.stage3.alice.core.criterion.ExternalReferenceKeyedCriterion" name="element">flashlight.lightCone3</property>
    <property name="propertyName">isShowing</property>
    <property class="java.lang.Boolean" name="value">false</property>
    <property class="edu.cmu.cs.stage3.util.HowMuch" name="howMuch">edu.cmu.cs.stage3.util.HowMuch[INSTANCE_AND_PARTS]</property>
    <property
        class="edu.cmu.cs.stage3.alice.core.style.TraditionalAnimationStyle" name="style">edu.cmu.cs.stage3.alice.core.style.TraditionalAnimationStyle[BEGIN_AND_END_GENTLY]</property>
    <property class="java.lang.Double" name="duration">1.0</property>
    <property name="isCommentedOut">false</property>
    <property name="isFirstClass">false</property>
    <property name="data">
        <entry>
            <key class="java.lang.String">edu.cmu.cs.stage3.alice.authoringtool.visibleProperties</key>
            <value class="java.lang.String">element,propertyName,value</value>
        </entry>
    </property>
</element>
